{"kills":3469,"wins":282,"last_hits":76124,"leaves":3,"heroes":{"shredder":{"kills":[15,0,6,6],"item_neutral":[0,0,0,0],"backpack_1":[0,0,0,0],"denies":[18,1,8,5],"backpack_2":[0,0,0,0],"backpack_0":[0,0,0,0],"leaves":0,"assists":[11,0,19,3],"loses":3,"xp_per_min":[721,186,709,587],"deaths":[3,0,12,4],"total_matches":8,"wins":1,"exp_per_min":[721,186,709,587],"gold_per_min":[654,172,424,465],"level":[21,4,25,20],"matches_id":[2912082308,3070236550,3312091111,4475698290],"match_id":[2912082308,3070236550,3312091111,4475698290],"friends":{"gela":{"wins":1,"loses":3,"total_matches":4},"knight":{"wins":1,"loses":1,"total_matches":2}},"last_hits":[168,4,170,187],"item_5":[71,0,180,11],"item_4":[180,11,11,29],"name":"Timbersaw","item_3":[11,0,127,121],"item_2":[1,182,1,69],"item_1":[121,216,178,36],"item_0":[127,36,90,242]},"dazzle":{"kills":[1],"item_neutral":[0],"backpack_1":[0],"denies":[4],"backpack_2":[0],"backpack_0":[0],"leaves":0,"assists":[12],"loses":0,"xp_per_min":[328],"deaths":[2],"total_matches":2,"wins":1,"exp_per_min":[328],"gold_per_min":[317],"level":[13],"matches_id":[3491715988],"match_id":[3491715988],"friends":{"gela":{"wins":1,"loses":0,"total_matches":1},"knight":{"wins":1,"loses":0,"total_matches":1}},"last_hits":[30],"item_5":[34],"item_4":[46],"name":"Dazzle","item_3":[0],"item_2":[254],"item_1":[79],"item_0":[180]},"kunkka":{"kills":[9,7,19],"item_neutral":[0,0,0],"backpack_1":[0,0,0],"denies":[2,2,9],"backpack_2":[0,0,0],"backpack_0":[0,46,0],"leaves":0,"assists":[32,24,23],"loses":1,"xp_per_min":[724,522,707],"deaths":[3,7,8],"total_matches":6,"wins":2,"exp_per_min":[724,522,707],"gold_per_min":[558,486,716],"level":[25,25,25],"matches_id":[3308278463,3943485920,4144522006],"match_id":[3308278463,3943485920,4144522006],"friends":{"gela":{"wins":2,"loses":1,"total_matches":3}},"last_hits":[226,259,635],"item_5":[141,141,133],"item_4":[141,232,220],"name":"Kunkka","item_3":[151,50,141],"item_2":[1,1,1],"item_1":[185,141,133],"item_0":[50,210,141]},"dragon_knight":{"kills":[7,8],"item_neutral":[0,0],"backpack_1":[0,0],"denies":[9,7],"backpack_2":[0,36],"backpack_0":[0,46],"leaves":0,"assists":[15,16],"loses":0,"xp_per_min":[667,644],"deaths":[3,3],"total_matches":4,"wins":2,"exp_per_min":[667,644],"gold_per_min":[621,543],"level":[22,22],"matches_id":[3787147202,4132724143],"match_id":[3787147202,4132724143],"friends":{"gela":{"wins":2,"loses":0,"total_matches":2},"knight":{"wins":1,"loses":0,"total_matches":1}},"last_hits":[199,200],"item_5":[65,178],"item_4":[185,185],"name":"Dragon Knight","item_3":[63,63],"item_2":[249,152],"item_1":[154,210],"item_0":[55,116]},"medusa":{"kills":[5],"item_neutral":[0],"backpack_1":[46],"denies":[7],"backpack_2":[0],"backpack_0":[0],"leaves":0,"assists":[12],"loses":0,"xp_per_min":[687],"deaths":[2],"total_matches":2,"wins":1,"exp_per_min":[687],"gold_per_min":[734],"level":[25],"matches_id":[3100946326],"match_id":[3100946326],"friends":{"gela":{"wins":1,"loses":0,"total_matches":1}},"last_hits":[378],"item_5":[147],"item_4":[212],"name":"Medusa","item_3":[50],"item_2":[158],"item_1":[160],"item_0":[123]},"keeper_of_the_light":{"kills":[4,3,2,3,2],"item_neutral":[0,0,0,0,357],"backpack_1":[0,0,244,37,0],"denies":[1,0,0,1,0],"backpack_2":[0,0,46,0,0],"backpack_0":[0,0,11,257,34],"leaves":0,"assists":[17,13,20,17,17],"loses":0,"xp_per_min":[480,348,487,478,485],"deaths":[3,0,11,1,5],"total_matches":10,"wins":5,"exp_per_min":[480,348,487,478,485],"gold_per_min":[392,399,348,575,332],"level":[20,14,23,25,18],"matches_id":[3491759412,3495178537,3577086455,3931609495,5790316015],"match_id":[3491759412,3495178537,3577086455,3931609495,5790316015],"friends":{"gela":{"wins":5,"loses":0,"total_matches":5},"knight":{"wins":2,"loses":0,"total_matches":2},"sparki":{"wins":1,"loses":0,"total_matches":1}},"last_hits":[92,80,105,459,79],"item_5":[102,214,129,256,102],"item_4":[214,0,214,220,214],"name":"Keep of the Light","item_3":[46,0,36,96,42],"item_2":[1,102,254,102,1],"item_1":[108,0,30,108,244],"item_0":[254,108,108,204,254]},"axe":{"kills":[15,16,13,7,15,10],"item_neutral":[0,0,0,0,0,0],"backpack_1":[214,0,0,0,125,0],"denies":[1,4,12,3,5,2],"backpack_2":[0,188,0,0,216,34],"backpack_0":[46,0,46,0,38,0],"leaves":0,"assists":[16,11,21,21,12,10],"loses":1,"xp_per_min":[659,635,685,580,709,495],"deaths":[7,4,6,8,6,4],"total_matches":12,"wins":5,"exp_per_min":[659,635,685,580,709,495],"gold_per_min":[518,555,631,522,522,450],"level":[25,25,25,25,25,19],"matches_id":[3641834629,3670665234,3722960714,3944965885,4241802071,5015189227],"match_id":[3641834629,3670665234,3722960714,3944965885,4241802071,5015189227],"friends":{"gela":{"wins":5,"loses":1,"total_matches":6},"mati":{"wins":1,"loses":0,"total_matches":1}},"last_hits":[228,299,341,394,217,140],"item_5":[114,102,158,102,102,102],"item_4":[125,48,125,220,50,73],"name":"Axe","item_3":[102,125,63,114,152,50],"item_2":[1,1,1,1,1,1],"item_1":[116,158,145,116,116,242],"item_0":[127,127,127,127,127,127]},"lich":{"kills":[12],"item_neutral":[0],"backpack_1":[0],"denies":[4],"backpack_2":[0],"backpack_0":[0],"leaves":0,"assists":[19],"loses":0,"xp_per_min":[613],"deaths":[6],"total_matches":2,"wins":1,"exp_per_min":[613],"gold_per_min":[491],"level":[23],"matches_id":[3057765254],"match_id":[3057765254],"friends":{"gela":{"wins":1,"loses":0,"total_matches":1}},"last_hits":[92],"item_5":[36],"item_4":[214],"name":"Lich","item_3":[46],"item_2":[102],"item_1":[244],"item_0":[231]},"furion":{"kills":[4,6,2,13,6],"item_neutral":[0,0,0,0,0],"backpack_1":[0,0,0,0,0],"denies":[1,14,6,6,20],"backpack_2":[0,0,46,0,0],"backpack_0":[0,0,0,0,46],"leaves":0,"assists":[16,12,19,35,10],"loses":1,"xp_per_min":[512,542,457,684,677],"deaths":[5,8,7,3,4],"total_matches":10,"wins":4,"exp_per_min":[512,542,457,684,677],"gold_per_min":[549,458,487,655,617],"level":[19,20,18,25,25],"matches_id":[3407891219,3435264995,3437384315,3504898099,3605136857],"match_id":[3407891219,3435264995,3437384315,3504898099,3605136857],"friends":{"gela":{"wins":4,"loses":1,"total_matches":5},"knight":{"wins":4,"loses":0,"total_matches":4}},"last_hits":[227,205,207,422,342],"item_5":[0,152,152,263,249],"item_4":[40,166,0,131,185],"name":"Narute's Prophet","item_3":[50,50,50,50,50],"item_2":[249,36,151,249,98],"item_1":[77,98,185,96,96],"item_0":[250,77,36,250,116]},"sniper":{"kills":[9,13,14,18],"item_neutral":[0,0,0,0],"backpack_1":[0,0,0,0],"denies":[8,16,4,7],"backpack_2":[0,16,0,46],"backpack_0":[0,36,46,0],"leaves":0,"assists":[10,18,15,18],"loses":0,"xp_per_min":[559,638,673,694],"deaths":[3,4,1,3],"total_matches":8,"wins":4,"exp_per_min":[559,638,673,694],"gold_per_min":[498,630,665,698],"level":[20,25,24,25],"matches_id":[3213130501,3322446455,3437436219,3718119814],"match_id":[3213130501,3322446455,3437436219,3718119814],"friends":{"gela":{"wins":4,"loses":0,"total_matches":4},"knight":{"wins":3,"loses":0,"total_matches":3},"mati":{"wins":1,"loses":0,"total_matches":1}},"last_hits":[203,303,278,320],"item_5":[0,147,263,135],"item_4":[46,212,149,26],"name":"Sniper","item_3":[50,63,63,63],"item_2":[263,263,135,263],"item_1":[212,166,158,158],"item_0":[158,139,172,139]},"rubick":{"kills":[8,0,2,6,10,6,5,3,5,5,5,3,5],"item_neutral":[0,0,0,0,0,0,0,0,0,0,0,0,0],"backpack_1":[0,0,0,0,0,0,0,0,0,0,73,0,88],"denies":[2,4,3,10,14,1,1,5,9,2,5,0,9],"backpack_2":[0,0,0,0,0,188,0,0,0,0,0,0,0],"backpack_0":[40,0,0,0,46,0,0,46,0,0,40,0,0],"leaves":0,"assists":[38,10,13,18,15,21,18,25,33,26,29,22,19],"loses":3,"xp_per_min":[702,316,429,469,655,569,360,477,605,488,568,472,596],"deaths":[6,1,8,9,7,6,7,4,3,13,7,0,1],"total_matches":26,"wins":10,"exp_per_min":[702,316,429,469,655,569,360,477,605,488,568,472,596],"gold_per_min":[497,282,358,480,503,381,319,378,433,321,370,315,385],"level":[25,17,22,25,23,22,18,17,25,25,23,18,19],"matches_id":[2912130912,3045608742,3057835995,3114976005,3495129379,3674146393,3857869668,4087590501,4359531678,4985963226,5028186344,5045836820,5117658504],"match_id":[2912130912,3045608742,3057835995,3114976005,3495129379,3674146393,3857869668,4087590501,4359531678,4985963226,5028186344,5045836820,5117658504],"friends":{"gela":{"wins":10,"loses":3,"total_matches":13},"knight":{"wins":6,"loses":2,"total_matches":8},"mati":{"wins":3,"loses":0,"total_matches":3}},"last_hits":[68,75,115,262,178,92,49,56,173,64,82,34,66],"item_5":[108,254,65,102,185,65,36,232,48,232,214,38,59],"item_4":[48,46,0,108,108,48,214,244,30,214,232,214,244],"name":"Rubick","item_3":[100,100,100,50,63,254,100,29,100,226,254,40,48],"item_2":[1,1,1,1,1,1,37,1,1,1,1,254,102],"item_1":[59,180,214,116,77,244,0,92,108,30,108,43,36],"item_0":[37,36,37,96,123,232,46,37,37,37,36,232,254]},"dark_willow":{"kills":[14,0,6,6,10,9,5,6],"item_neutral":[0,0,0,0,0,0,0,0],"backpack_1":[59,0,0,46,0,0,46,46],"denies":[18,6,4,4,5,1,0,14],"backpack_2":[0,0,0,0,0,0,0,0],"backpack_0":[46,31,0,0,46,46,218,40],"leaves":0,"assists":[14,15,14,4,19,16,20,17],"loses":3,"xp_per_min":[679,395,427,377,551,468,393,577],"deaths":[3,14,2,4,5,6,6,7],"total_matches":16,"wins":5,"exp_per_min":[679,395,427,377,551,468,393,577],"gold_per_min":[579,239,398,465,387,339,304,429],"level":[25,18,16,13,22,22,18,23],"matches_id":[3547717633,3549490322,3551183953,3552953591,3560896240,3566131449,3577152509,3722901999],"match_id":[3547717633,3549490322,3551183953,3552953591,3560896240,3566131449,3577152509,3722901999],"friends":{"gela":{"wins":5,"loses":3,"total_matches":8},"knight":{"wins":4,"loses":2,"total_matches":6}},"last_hits":[185,58,61,69,63,103,38,172],"item_5":[259,40,46,131,254,259,100,123],"item_4":[48,180,77,23,180,29,77,48],"name":"Dark Willow","item_3":[190,42,100,180,190,30,259,100],"item_2":[1,34,36,1,1,1,254,1],"item_1":[123,65,259,190,223,190,36,0],"item_0":[119,244,231,36,36,256,180,190]},"wisp":{"kills":[4,2],"item_neutral":[0,0],"backpack_1":[46,40],"denies":[0,0],"backpack_2":[0,0],"backpack_0":[0,46],"leaves":1,"assists":[11,21],"loses":1,"xp_per_min":[432,352],"deaths":[4,8],"total_matches":4,"wins":1,"exp_per_min":[432,352],"gold_per_min":[340,328],"level":[22,16],"matches_id":[3564359148,3730012371],"match_id":[3564359148,3730012371],"friends":{"gela":{"wins":1,"loses":1,"total_matches":2},"knight":{"wins":1,"loses":1,"total_matches":2}},"last_hits":[117,40],"item_5":[92,37],"item_4":[256,43],"name":"Wisp","item_3":[63,63],"item_2":[254,36],"item_1":[41,41],"item_0":[226,267]},"skeleton_king":{"kills":[17,14],"item_neutral":[0,0],"backpack_1":[0,46],"denies":[19,22],"backpack_2":[0,0],"backpack_0":[36,0],"leaves":0,"assists":[22,17],"loses":0,"xp_per_min":[575,613],"deaths":[4,0],"total_matches":4,"wins":2,"exp_per_min":[575,613],"gold_per_min":[724,618],"level":[25,21],"matches_id":[2912278884,4130628677],"match_id":[2912278884,4130628677],"friends":{"gela":{"wins":2,"loses":0,"total_matches":2},"knight":{"wins":2,"loses":0,"total_matches":2}},"last_hits":[419,213],"item_5":[147,137],"item_4":[137,252],"name":"Skeleton King","item_3":[63,63],"item_2":[1,1],"item_1":[112,135],"item_0":[110,127]},"necrolyte":{"kills":[15],"item_neutral":[0],"backpack_1":[0],"denies":[13],"backpack_2":[0],"backpack_0":[0],"leaves":0,"assists":[21],"loses":0,"xp_per_min":[694],"deaths":[8],"total_matches":2,"wins":1,"exp_per_min":[694],"gold_per_min":[527],"level":[25],"matches_id":[3526753581],"match_id":[3526753581],"friends":{"gela":{"wins":1,"loses":0,"total_matches":1},"knight":{"wins":1,"loses":0,"total_matches":1}},"last_hits":[414],"item_5":[137],"item_4":[48],"name":"Necrophos","item_3":[108],"item_2":[102],"item_1":[204],"item_0":[190]},"puck":{"kills":[5],"item_neutral":[0],"backpack_1":[16],"denies":[14],"backpack_2":[0],"backpack_0":[40],"leaves":0,"assists":[14],"loses":0,"xp_per_min":[439],"deaths":[7],"total_matches":2,"wins":1,"exp_per_min":[439],"gold_per_min":[418],"level":[17],"matches_id":[4447542356],"match_id":[4447542356],"friends":{"gela":{"wins":1,"loses":0,"total_matches":1}},"last_hits":[109],"item_5":[38],"item_4":[77],"name":"Puck","item_3":[63],"item_2":[1],"item_1":[123],"item_0":[41]},"troll_warlord":{"kills":[16,11,7,8],"item_neutral":[0,0,0,381],"backpack_1":[152,0,0,0],"denies":[12,11,8,26],"backpack_2":[0,0,0,0],"backpack_0":[46,0,0,0],"leaves":0,"assists":[9,19,16,14],"loses":0,"xp_per_min":[833,642,658,633],"deaths":[2,3,4,5],"total_matches":8,"wins":4,"exp_per_min":[833,642,658,633],"gold_per_min":[713,641,554,521],"level":[25,25,24,26],"matches_id":[3200658260,3318533106,3410231410,5838208452],"match_id":[3200658260,3318533106,3410231410,5838208452],"friends":{"gela":{"wins":4,"loses":0,"total_matches":4},"knight":{"wins":2,"loses":0,"total_matches":2},"sparki":{"wins":1,"loses":0,"total_matches":1},"mati":{"wins":2,"loses":0,"total_matches":2}},"last_hits":[336,397,305,259],"item_5":[160,112,212,154],"item_4":[154,81,26,75],"name":"Troll Warlord","item_3":[50,48,50,50],"item_2":[81,196,147,208],"item_1":[139,160,53,6],"item_0":[116,116,116,116]},"phantom_assasin":{"kills":[7,7,21,23],"item_neutral":[0,0,0,0],"backpack_1":[0,216,0,36],"denies":[17,4,12,12],"backpack_2":[0,46,0,75],"backpack_0":[11,0,75,0],"leaves":0,"assists":[5,14,15,12],"loses":0,"xp_per_min":[494,682,803,794],"deaths":[1,7,6,1],"total_matches":8,"wins":4,"exp_per_min":[494,682,803,794],"gold_per_min":[641,541,624,612],"level":[16,25,25,25],"matches_id":[3479921415,3674093158,4241737136,5068663186],"match_id":[3479921415,3674093158,4241737136,5068663186],"friends":{"gela":{"wins":4,"loses":0,"total_matches":4},"knight":{"wins":2,"loses":0,"total_matches":2},"mati":{"wins":1,"loses":0,"total_matches":1}},"last_hits":[161,241,344,187],"item_5":[168,0,168,160],"item_4":[212,81,63,168],"name":"Phantom Assasin","item_3":[50,50,225,50],"item_2":[172,208,208,143],"item_1":[71,168,156,117],"item_0":[139,116,116,116]},"ursa":{"kills":[14,15],"item_neutral":[0,0],"backpack_1":[0,0],"denies":[7,1],"backpack_2":[0,0],"backpack_0":[0,0],"leaves":0,"assists":[13,13],"loses":0,"xp_per_min":[581,763],"deaths":[5,1],"total_matches":4,"wins":2,"exp_per_min":[581,763],"gold_per_min":[618,584],"level":[18,25],"matches_id":[3728659995,5127171684],"match_id":[3728659995,5127171684],"friends":{"gela":{"wins":2,"loses":0,"total_matches":2},"knight":{"wins":1,"loses":0,"total_matches":1},"mati":{"wins":1,"loses":0,"total_matches":1}},"last_hits":[134,262],"item_5":[46,174],"item_4":[108,26],"name":"Ursa","item_3":[50,50],"item_2":[1,1],"item_1":[174,208],"item_0":[172,116]},"venomancer":{"kills":[5],"item_neutral":[0],"backpack_1":[0],"denies":[6],"backpack_2":[0],"backpack_0":[0],"leaves":0,"assists":[28],"loses":0,"xp_per_min":[595],"deaths":[11],"total_matches":2,"wins":1,"exp_per_min":[595],"gold_per_min":[606],"level":[28],"matches_id":[5159255690],"match_id":[5159255690],"friends":{"gela":{"wins":1,"loses":0,"total_matches":1},"knight":{"wins":1,"loses":0,"total_matches":1}},"last_hits":[394],"item_5":[119],"item_4":[300],"name":"Venomancer","item_3":[50],"item_2":[1],"item_1":[90],"item_0":[96]},"templar_assasin":{"kills":[13],"item_neutral":[0],"backpack_1":[46],"denies":[8],"backpack_2":[0],"backpack_0":[36],"leaves":0,"assists":[20],"loses":0,"xp_per_min":[715],"deaths":[7],"total_matches":2,"wins":1,"exp_per_min":[715],"gold_per_min":[560],"level":[25],"matches_id":[3705595391],"match_id":[3705595391],"friends":{"gela":{"wins":1,"loses":0,"total_matches":1},"knight":{"wins":1,"loses":0,"total_matches":1}},"last_hits":[271],"item_5":[212],"item_4":[168],"name":"Templar Assasin","item_3":[63],"item_2":[1],"item_1":[123],"item_0":[98]},"meepo":{"kills":[12,5,1],"item_neutral":[0,0,0],"backpack_1":[46,173,182],"denies":[6,5,1],"backpack_2":[0,46,0],"backpack_0":[63,71,11],"leaves":0,"assists":[3,6,15],"loses":1,"xp_per_min":[982,511,584],"deaths":[1,11,4],"total_matches":6,"wins":2,"exp_per_min":[982,511,584],"gold_per_min":[770,368,567],"level":[25,19,17],"matches_id":[3386435340,3426049226,5124080737],"match_id":[3386435340,3426049226,5124080737],"friends":{"gela":{"wins":2,"loses":1,"total_matches":3},"knight":{"wins":1,"loses":0,"total_matches":1}},"last_hits":[342,176,168],"item_5":[263,212,75],"item_4":[236,22,75],"name":"Meepo","item_3":[176,63,63],"item_2":[1,1,1],"item_1":[108,236,75],"item_0":[48,22,176]},"chaos_knight":{"kills":[21,15],"item_neutral":[0,0],"backpack_1":[0,0],"denies":[1,6],"backpack_2":[0,11],"backpack_0":[46,0],"leaves":0,"assists":[15,11],"loses":0,"xp_per_min":[807,601],"deaths":[8,4],"total_matches":4,"wins":2,"exp_per_min":[807,601],"gold_per_min":[694,603],"level":[25,21],"matches_id":[3749756039,4601951483],"match_id":[3749756039,4601951483],"friends":{"gela":{"wins":2,"loses":0,"total_matches":2}},"last_hits":[236,169],"item_5":[63,114],"item_4":[114,73],"name":"Chaos Knight","item_3":[225,63],"item_2":[1,1],"item_1":[252,65],"item_0":[116,151]},"broodmother":{"kills":[11],"item_neutral":[0],"backpack_1":[0],"denies":[7],"backpack_2":[178],"backpack_0":[0],"leaves":0,"assists":[9],"loses":0,"xp_per_min":[780],"deaths":[2],"total_matches":2,"wins":1,"exp_per_min":[780],"gold_per_min":[533],"level":[25],"matches_id":[3765039444],"match_id":[3765039444],"friends":{"gela":{"wins":1,"loses":0,"total_matches":1},"knight":{"wins":1,"loses":0,"total_matches":1}},"last_hits":[226],"item_5":[149],"item_4":[168],"name":"Broodmother","item_3":[50],"item_2":[229],"item_1":[98],"item_0":[116]},"morphling":{"kills":[3,17,21,26,3],"item_neutral":[0,0,0,0,0],"backpack_1":[0,0,0,46,75],"denies":[16,16,18,15,7],"backpack_2":[0,0,0,0,0],"backpack_0":[46,46,46,0,36],"leaves":0,"assists":[13,10,3,17,9],"loses":1,"xp_per_min":[505,857,668,700,470],"deaths":[5,1,4,10,2],"total_matches":10,"wins":4,"exp_per_min":[505,857,668,700,470],"gold_per_min":[382,776,705,560,495],"level":[22,25,21,25,14],"matches_id":[3291632194,3487495416,3766581166,3931725742,4087511685],"match_id":[3291632194,3487495416,3766581166,3931725742,4087511685],"friends":{"gela":{"wins":4,"loses":1,"total_matches":5},"knight":{"wins":2,"loses":0,"total_matches":2}},"last_hits":[134,363,184,318,129],"item_5":[147,139,123,249,236],"item_4":[164,135,236,160,24],"name":"Morphling","item_3":[63,63,63,63,63],"item_2":[263,176,176,176,46],"item_1":[212,123,36,123,212],"item_0":[178,160,212,52,69]},"ember_spirit":{"kills":[19,15,13,6,6],"item_neutral":[0,0,0,0,0],"backpack_1":[0,0,0,0,0],"denies":[13,8,5,10,7],"backpack_2":[0,0,0,0,0],"backpack_0":[0,0,0,0,0],"leaves":0,"assists":[15,16,16,9,17],"loses":2,"xp_per_min":[684,587,727,357,451],"deaths":[5,8,8,3,2],"total_matches":10,"wins":3,"exp_per_min":[684,587,727,357,451],"gold_per_min":[681,502,576,334,454],"level":[25,25,25,17,20],"matches_id":[3440950076,3625717380,3787212205,3992721412,5001655388],"match_id":[3440950076,3625717380,3787212205,3992721412,5001655388],"friends":{"gela":{"wins":3,"loses":2,"total_matches":5},"knight":{"wins":2,"loses":2,"total_matches":4}},"last_hits":[400,278,309,107,165],"item_5":[141,158,141,0,75],"item_4":[48,48,46,0,166],"name":"Ember_spirit","item_3":[0,190,63,0,50],"item_2":[249,1,1,0,108],"item_1":[133,41,2,0,129],"item_0":[145,123,145,0,116]},"invoker":{"kills":[9,15,23,12,5,5,8,16,7,6,7,18,12,13,2,7,5,5],"item_neutral":[0,0,0,0,0,0,0,0,0,0,0,0,0,0,0,0,0,0],"backpack_1":[0,0,0,0,0,0,0,0,16,0,0,0,0,0,0,0,0,0],"denies":[19,15,8,19,27,16,15,36,21,9,10,21,12,17,12,16,9,4],"backpack_2":[0,0,0,0,0,0,0,0,0,0,0,0,0,0,0,0,0,0],"backpack_0":[46,0,0,0,0,0,0,0,241,0,46,46,0,0,0,0,0,0],"leaves":0,"assists":[5,5,16,13,9,15,12,13,13,10,15,19,11,6,3,19,8,15],"loses":5,"xp_per_min":[676,663,506,639,595,768,716,858,564,594,605,657,718,483,339,664,428,593],"deaths":[2,5,7,5,2,2,4,4,5,1,5,6,3,0,5,2,1,11],"total_matches":36,"wins":13,"exp_per_min":[676,663,506,639,595,768,716,858,564,594,605,657,718,483,339,664,428,593],"gold_per_min":[672,840,676,601,640,642,623,770,455,659,505,651,558,497,291,512,356,409],"level":[25,25,25,25,19,25,23,25,23,19,23,25,25,16,12,23,15,22],"matches_id":[2990429296,3052427513,3107579002,3338472664,3340476008,3637782941,3637951567,3641915422,3661128575,3667338954,3787305889,3805192308,4070908484,4228826037,4357088446,4674726696,4740377011,4955890250],"match_id":[2990429296,3052427513,3107579002,3338472664,3340476008,3637782941,3637951567,3641915422,3661128575,3667338954,3787305889,3805192308,4070908484,4228826037,4357088446,4674726696,4740377011,4955890250],"friends":{"gela":{"wins":13,"loses":5,"total_matches":18},"knight":{"wins":9,"loses":2,"total_matches":11},"mati":{"wins":3,"loses":2,"total_matches":5}},"last_hits":[257,377,352,466,180,279,196,386,219,157,189,278,269,102,71,201,96,128],"item_5":[102,108,235,123,108,65,65,65,65,108,212,63,123,0,23,36,185,48],"item_4":[108,48,48,48,48,48,48,48,48,0,123,123,48,77,77,108,29,69],"name":"Invoker","item_3":[50,96,96,96,65,235,235,96,166,50,63,100,40,48,63,50,21,108],"item_2":[96,1,1,235,1,1,1,1,1,98,102,1,1,1,77,98,77,77],"item_1":[65,123,123,108,129,123,77,235,77,77,108,108,108,108,77,92,108,65],"item_0":[158,235,110,116,77,108,108,123,108,65,37,116,116,77,0,116,77,88]},"obsidian_destroyer":{"kills":[21,13,6,14,16,4,8,5,19,16,3,11,16,7,9],"item_neutral":[0,675,0,589,361,675,357,571,573,336,287,287,309,675,675],"backpack_1":[0,65,0,0,0,0,0,0,0,0,0,0,0,0,0],"denies":[38,14,12,6,9,5,12,3,8,6,7,8,9,8,21],"backpack_2":[0,0,0,0,0,40,0,0,0,232,0,0,0,0,16],"backpack_0":[46,24,0,0,16,0,16,0,0,0,0,16,0,257,0],"leaves":0,"assists":[14,2,6,11,19,6,7,5,15,15,6,15,19,12,5],"loses":5,"xp_per_min":[704,839,454,658,649,402,417,580,790,713,289,434,692,666,468],"deaths":[3,3,2,3,7,7,1,6,1,8,11,0,1,5,7],"total_matches":30,"wins":10,"exp_per_min":[704,839,454,658,649,402,417,580,790,713,289,434,692,666,468],"gold_per_min":[579,728,373,520,479,314,491,430,620,468,228,436,555,489,382],"level":[25,26,10,19,23,19,14,24,26,26,12,16,22,24,21],"matches_id":[3265600252,5784278014,5795815427,5798536495,5798567365,5798670866,5800083733,5800118196,5803301578,5803371358,5804843233,5809391947,5811199379,5814386166,5843789004],"match_id":[3265600252,5784278014,5795815427,5798536495,5798567365,5798670866,5800083733,5800118196,5803301578,5803371358,5804843233,5809391947,5811199379,5814386166,5843789004],"friends":{"gela":{"wins":10,"loses":5,"total_matches":15},"knight":{"wins":1,"loses":0,"total_matches":1},"sparki":{"wins":7,"loses":4,"total_matches":11},"mati":{"wins":5,"loses":2,"total_matches":7}},"last_hits":[325,327,44,100,104,166,95,269,205,169,37,89,145,182,198],"item_5":[263,277,0,0,244,244,29,232,232,119,27,244,235,232,60],"item_4":[63,534,0,244,232,29,232,29,48,214,0,48,48,48,214],"name":"Outworld Devourer","item_3":[96,96,29,29,180,102,223,223,223,37,214,232,223,223,223],"item_2":[1,1,223,223,223,223,1,1,1,223,223,223,1,1,1],"item_1":[119,63,0,108,108,232,59,112,119,116,0,108,108,123,232],"item_0":[116,116,65,235,116,116,9,135,123,108,36,0,244,116,116]},"abyssal_underlord":{"kills":[4],"item_neutral":[0],"backpack_1":[0],"denies":[6],"backpack_2":[0],"backpack_0":[0],"leaves":0,"assists":[11],"loses":0,"xp_per_min":[540],"deaths":[5],"total_matches":2,"wins":1,"exp_per_min":[540],"gold_per_min":[514],"level":[19],"matches_id":[3665236029],"match_id":[3665236029],"friends":{"gela":{"wins":1,"loses":0,"total_matches":1},"knight":{"wins":1,"loses":0,"total_matches":1}},"last_hits":[137],"item_5":[90],"item_4":[46],"name":"Abyssal Underlord","item_3":[30],"item_2":[36],"item_1":[231],"item_0":[40]},"lion":{"kills":[7,6,9,4],"item_neutral":[0,0,0,0],"backpack_1":[42,0,0,310],"denies":[7,1,7,2],"backpack_2":[0,0,0,0],"backpack_0":[46,0,257,0],"leaves":0,"assists":[26,12,31,7],"loses":2,"xp_per_min":[525,335,568,365],"deaths":[11,6,12,9],"total_matches":8,"wins":2,"exp_per_min":[525,335,568,365],"gold_per_min":[356,263,391,239],"level":[25,15,25,16],"matches_id":[3373144701,4594215779,4955958229,5142905677],"match_id":[3373144701,4594215779,4955958229,5142905677],"friends":{"gela":{"wins":2,"loses":2,"total_matches":4},"knight":{"wins":2,"loses":0,"total_matches":2},"mati":{"wins":1,"loses":0,"total_matches":1}},"last_hits":[128,24,49,33],"item_5":[102,244,232,244],"item_4":[214,214,214,214],"name":"Lion","item_3":[100,36,37,36],"item_2":[1,1,1,218],"item_1":[123,0,256,73],"item_0":[176,38,42,254]},"clinkz":{"kills":[16,7],"item_neutral":[0,0],"backpack_1":[0,36],"denies":[21,3],"backpack_2":[0,46],"backpack_0":[0,240],"leaves":0,"assists":[16,4],"loses":0,"xp_per_min":[626,389],"deaths":[2,2],"total_matches":4,"wins":2,"exp_per_min":[626,389],"gold_per_min":[592,442],"level":[21,15],"matches_id":[3504782248,4087545267],"match_id":[3504782248,4087545267],"friends":{"gela":{"wins":2,"loses":0,"total_matches":2},"knight":{"wins":1,"loses":0,"total_matches":1}},"last_hits":[129,97],"item_5":[212,178],"item_4":[29,212],"name":"Clinkz","item_3":[229,63],"item_2":[250,174],"item_1":[168,117],"item_0":[178,116]},"void_spirit":{"kills":[11,10],"item_neutral":[0,0],"backpack_1":[0,0],"denies":[10,12],"backpack_2":[0,38],"backpack_0":[0,0],"leaves":0,"assists":[19,10],"loses":0,"xp_per_min":[626,659],"deaths":[3,3],"total_matches":4,"wins":2,"exp_per_min":[626,659],"gold_per_min":[524,524],"level":[23,23],"matches_id":[5158039416,5159220417],"match_id":[5158039416,5159220417],"friends":{"gela":{"wins":2,"loses":0,"total_matches":2},"knight":{"wins":2,"loses":0,"total_matches":2}},"last_hits":[220,221],"item_5":[98,123],"item_4":[29,378],"name":"Void Spirit","item_3":[100,100],"item_2":[123,50],"item_1":[273,273],"item_0":[190,116]},"storm_spirit":{"kills":[22,11],"item_neutral":[0,0],"backpack_1":[0,41],"denies":[23,10],"backpack_2":[0,0],"backpack_0":[0,0],"leaves":0,"assists":[10,20],"loses":0,"xp_per_min":[863,657],"deaths":[2,0],"total_matches":4,"wins":2,"exp_per_min":[863,657],"gold_per_min":[759,548],"level":[25,25],"matches_id":[3172824649,4248114030],"match_id":[3172824649,4248114030],"friends":{"gela":{"wins":2,"loses":0,"total_matches":2}},"last_hits":[250,267],"item_5":[40,259],"item_4":[121,29],"name":"Storm Spirit","item_3":[63,121],"item_2":[250,98],"item_1":[121,119],"item_0":[123,116]},"centaur":{"kills":[17],"item_neutral":[0],"backpack_1":[147],"denies":[23],"backpack_2":[0],"backpack_0":[46],"leaves":0,"assists":[15],"loses":0,"xp_per_min":[658],"deaths":[3],"total_matches":2,"wins":1,"exp_per_min":[658],"gold_per_min":[668],"level":[25],"matches_id":[3107477640],"match_id":[3107477640],"friends":{"gela":{"wins":1,"loses":0,"total_matches":1}},"last_hits":[271],"item_5":[114],"item_4":[108],"name":"Centaur Warruner","item_3":[50],"item_2":[1],"item_1":[90],"item_0":[127]},"winter_wyvern":{"kills":[7],"item_neutral":[0],"backpack_1":[0],"denies":[2],"backpack_2":[46],"backpack_0":[0],"leaves":0,"assists":[20],"loses":0,"xp_per_min":[500],"deaths":[1],"total_matches":2,"wins":1,"exp_per_min":[500],"gold_per_min":[370],"level":[19],"matches_id":[3491810234],"match_id":[3491810234],"friends":{"gela":{"wins":1,"loses":0,"total_matches":1},"knight":{"wins":1,"loses":0,"total_matches":1}},"last_hits":[63],"item_5":[102],"item_4":[181],"name":"Winter Wyvern","item_3":[180],"item_2":[1],"item_1":[36],"item_0":[254]},"zeus":{"kills":[14,13,4,12,5],"item_neutral":[0,0,0,335,675],"backpack_1":[0,0,0,0,0],"denies":[8,2,2,1,7],"backpack_2":[0,41,0,0,0],"backpack_0":[41,46,41,0,41],"leaves":0,"assists":[26,28,17,20,23],"loses":0,"xp_per_min":[566,728,744,713,656],"deaths":[9,7,6,4,7],"total_matches":10,"wins":5,"exp_per_min":[566,728,744,713,656],"gold_per_min":[539,484,451,555,492],"level":[25,25,23,26,28],"matches_id":[2892891949,3259391365,4690196287,5784312732,5823125523],"match_id":[2892891949,3259391365,4690196287,5784312732,5823125523],"friends":{"gela":{"wins":5,"loses":0,"total_matches":5},"knight":{"wins":2,"loses":0,"total_matches":2},"sparki":{"wins":2,"loses":0,"total_matches":2},"mati":{"wins":1,"loses":0,"total_matches":1}},"last_hits":[243,223,143,241,230],"item_5":[263,108,180,277,235],"item_4":[48,48,232,232,48],"name":"Zeus","item_3":[100,100,259,244,37],"item_2":[1,1,1,48,1],"item_1":[123,235,60,108,108],"item_0":[232,190,37,110,110]},"dark_seer":{"kills":[7],"item_neutral":[0],"backpack_1":[0],"denies":[0],"backpack_2":[0],"backpack_0":[0],"leaves":0,"assists":[32],"loses":0,"xp_per_min":[601],"deaths":[0],"total_matches":2,"wins":1,"exp_per_min":[601],"gold_per_min":[464],"level":[22],"matches_id":[3572180543],"match_id":[3572180543],"friends":{"gela":{"wins":1,"loses":0,"total_matches":1},"knight":{"wins":1,"loses":0,"total_matches":1},"mati":{"wins":1,"loses":0,"total_matches":1}},"last_hits":[138],"item_5":[102],"item_4":[46],"name":"Dark Seer","item_3":[231],"item_2":[1],"item_1":[90],"item_0":[178]},"gyrocopter":{"kills":[11],"item_neutral":[0],"backpack_1":[0],"denies":[14],"backpack_2":[0],"backpack_0":[0],"leaves":0,"assists":[7],"loses":0,"xp_per_min":[737],"deaths":[3],"total_matches":2,"wins":1,"exp_per_min":[737],"gold_per_min":[730],"level":[25],"matches_id":[3721333628],"match_id":[3721333628],"friends":{"gela":{"wins":1,"loses":0,"total_matches":1}},"last_hits":[390],"item_5":[139],"item_4":[154],"name":"Gyrocopter","item_3":[50],"item_2":[263],"item_1":[156],"item_0":[116]},"tiny":{"kills":[11,22,6,14,0,11,8,5],"item_neutral":[0,0,0,0,0,0,0,0],"backpack_1":[46,0,0,0,0,0,0,0],"denies":[15,10,12,30,15,9,7,11],"backpack_2":[0,0,0,0,16,0,0,0],"backpack_0":[0,46,0,46,0,0,178,11],"leaves":0,"assists":[10,17,4,15,0,16,10,8],"loses":4,"xp_per_min":[679,440,480,755,433,641,683,481],"deaths":[2,6,5,4,0,3,11,7],"total_matches":16,"wins":4,"exp_per_min":[679,440,480,755,433,641,683,481],"gold_per_min":[815,709,432,624,676,618,451,389],"level":[25,25,17,25,12,20,25,18],"matches_id":[3109367558,3115068007,3162401433,3320536897,3478142091,3570222817,4433892518,5151267080],"match_id":[3109367558,3115068007,3162401433,3320536897,3478142091,3570222817,4433892518,5151267080],"friends":{"gela":{"wins":4,"loses":4,"total_matches":8},"knight":{"wins":3,"loses":1,"total_matches":4}},"last_hits":[355,417,119,363,127,161,220,148],"item_5":[63,139,11,249,46,67,249,326],"item_4":[112,112,252,108,182,112,252,252],"name":"Tiny","item_3":[96,135,63,63,63,63,63,63],"item_2":[1,1,1,1,152,152,1,8],"item_1":[247,108,21,112,108,46,51,185],"item_0":[116,116,16,116,11,154,149,36]},"shadow_demon":{"kills":[1,2],"item_neutral":[0,300],"backpack_1":[0,0],"denies":[3,0],"backpack_2":[0,244],"backpack_0":[0,290],"leaves":0,"assists":[18,33],"loses":0,"xp_per_min":[479,666],"deaths":[4,1],"total_matches":4,"wins":2,"exp_per_min":[479,666],"gold_per_min":[336,394],"level":[20,24],"matches_id":[5040902415,5834011608],"match_id":[5040902415,5834011608],"friends":{"gela":{"wins":2,"loses":0,"total_matches":2},"knight":{"wins":1,"loses":0,"total_matches":1},"sparki":{"wins":1,"loses":0,"total_matches":1}},"last_hits":[72,50],"item_5":[188,108],"item_4":[214,214],"name":"Shadow Demon","item_3":[36,100],"item_2":[102,0],"item_1":[232,232],"item_0":[0,218]},"vengefulspirit":{"kills":[8],"item_neutral":[0],"backpack_1":[0],"denies":[14],"backpack_2":[0],"backpack_0":[0],"leaves":0,"assists":[26],"loses":0,"xp_per_min":[538],"deaths":[12],"total_matches":2,"wins":1,"exp_per_min":[538],"gold_per_min":[504],"level":[28],"matches_id":[5164483173],"match_id":[5164483173],"friends":{"gela":{"wins":1,"loses":0,"total_matches":1},"knight":{"wins":1,"loses":0,"total_matches":1}},"last_hits":[389],"item_5":[154],"item_4":[139],"name":"Vengeful Spirit","item_3":[50],"item_2":[263],"item_1":[156],"item_0":[116]},"crystal_maiden":{"kills":[10,1],"item_neutral":[0,0],"backpack_1":[46,188],"denies":[1,3],"backpack_2":[42,244],"backpack_0":[40,0],"leaves":0,"assists":[25,21],"loses":0,"xp_per_min":[649,546],"deaths":[8,4],"total_matches":4,"wins":2,"exp_per_min":[649,546],"gold_per_min":[450,380],"level":[25,21],"matches_id":[3370725559,5044226998],"match_id":[3370725559,5044226998],"friends":{"gela":{"wins":2,"loses":0,"total_matches":2},"knight":{"wins":2,"loses":0,"total_matches":2},"mati":{"wins":1,"loses":0,"total_matches":1}},"last_hits":[133,90],"item_5":[108,73],"item_4":[214,214],"name":"Crystal Maiden","item_3":[100,254],"item_2":[1,102],"item_1":[190,40],"item_0":[116,116]},"legion_commander":{"kills":[21,10],"item_neutral":[0,0],"backpack_1":[0,43],"denies":[8,17],"backpack_2":[0,0],"backpack_0":[46,11],"leaves":0,"assists":[9,14],"loses":0,"xp_per_min":[771,588],"deaths":[6,2],"total_matches":4,"wins":2,"exp_per_min":[771,588],"gold_per_min":[508,517],"level":[25,21],"matches_id":[3322510278,5158076481],"match_id":[3322510278,5158076481],"friends":{"gela":{"wins":2,"loses":0,"total_matches":2},"knight":{"wins":1,"loses":0,"total_matches":1},"mati":{"wins":1,"loses":0,"total_matches":1}},"last_hits":[336,168],"item_5":[152,378],"item_4":[112,168],"name":"Legion Commander","item_3":[96,50],"item_2":[1,1],"item_1":[108,116],"item_0":[50,127]},"nyx_assassin":{"kills":[10,7,11],"item_neutral":[0,0,0],"backpack_1":[0,46,212],"denies":[2,13,13],"backpack_2":[0,0,40],"backpack_0":[0,0,0],"leaves":0,"assists":[20,14,28],"loses":0,"xp_per_min":[660,600,629],"deaths":[3,6,10],"total_matches":6,"wins":3,"exp_per_min":[660,600,629],"gold_per_min":[429,510,524],"level":[23,24,25],"matches_id":[3585062434,3761489897,3810527051],"match_id":[3585062434,3761489897,3810527051],"friends":{"gela":{"wins":3,"loses":0,"total_matches":3},"knight":{"wins":2,"loses":0,"total_matches":2}},"last_hits":[40,125,163],"item_5":[65,65,37],"item_4":[46,180,48],"name":"Nyx Assassin","item_3":[100,100,223],"item_2":[102,1,1],"item_1":[108,108,65],"item_0":[180,223,119]},"abaddon":{"kills":[3],"item_neutral":[0],"backpack_1":[0],"denies":[0],"backpack_2":[0],"backpack_0":[4],"leaves":0,"assists":[19],"loses":0,"xp_per_min":[518],"deaths":[6],"total_matches":2,"wins":1,"exp_per_min":[518],"gold_per_min":[416],"level":[19],"matches_id":[3495092805],"match_id":[3495092805],"friends":{"gela":{"wins":1,"loses":0,"total_matches":1},"knight":{"wins":1,"loses":0,"total_matches":1}},"last_hits":[47],"item_5":[90],"item_4":[19],"name":"Abaddon","item_3":[50],"item_2":[65],"item_1":[127],"item_0":[36]},"shadow_field":{"kills":[34,12,13,6,7,7,12,10],"item_neutral":[0,0,0,0,0,0,0,0],"backpack_1":[0,41,0,237,0,0,0,0],"denies":[23,29,23,15,17,4,14,19],"backpack_2":[0,0,0,46,0,0,0,0],"backpack_0":[41,0,0,212,0,24,212,63],"leaves":0,"assists":[9,10,19,10,6,3,13,8],"loses":3,"xp_per_min":[909,703,684,586,471,500,756,677],"deaths":[4,2,5,8,7,12,9,7],"total_matches":16,"wins":5,"exp_per_min":[909,703,684,586,471,500,756,677],"gold_per_min":[968,622,478,483,563,455,581,661],"level":[25,25,25,25,17,18,25,25],"matches_id":[3213212009,3259321884,3276574871,3667207303,3805155394,3806779192,3823906838,3843173126],"match_id":[3213212009,3259321884,3276574871,3667207303,3805155394,3806779192,3823906838,3843173126],"friends":{"gela":{"wins":5,"loses":3,"total_matches":8},"knight":{"wins":5,"loses":2,"total_matches":7}},"last_hits":[445,337,308,369,175,156,233,560],"item_5":[263,263,152,176,212,131,185,147],"item_4":[48,48,212,48,48,185,48,236],"name":"Shadow Field","item_3":[250,147,63,100,100,63,100,135],"item_2":[1,1,263,1,1,152,1,1],"item_1":[139,249,166,152,185,212,37,139],"item_0":[147,116,116,116,36,46,116,116]},"enigma":{"kills":[6],"item_neutral":[0],"backpack_1":[0],"denies":[27],"backpack_2":[0],"backpack_0":[0],"leaves":0,"assists":[7],"loses":0,"xp_per_min":[424],"deaths":[0],"total_matches":2,"wins":1,"exp_per_min":[424],"gold_per_min":[606],"level":[12],"matches_id":[3761377289],"match_id":[3761377289],"friends":{"gela":{"wins":1,"loses":0,"total_matches":1},"knight":{"wins":1,"loses":0,"total_matches":1}},"last_hits":[74],"item_5":[180],"item_4":[46],"name":"Enigma","item_3":[178],"item_2":[1],"item_1":[79],"item_0":[21]},"mirana":{"kills":[7],"item_neutral":[0],"backpack_1":[0],"denies":[9],"backpack_2":[36],"backpack_0":[46],"leaves":0,"assists":[20],"loses":0,"xp_per_min":[533],"deaths":[2],"total_matches":2,"wins":1,"exp_per_min":[533],"gold_per_min":[509],"level":[20],"matches_id":[4089571953],"match_id":[4089571953],"friends":{"gela":{"wins":1,"loses":0,"total_matches":1},"knight":{"wins":1,"loses":0,"total_matches":1}},"last_hits":[182],"item_5":[170],"item_4":[135],"name":"Mirana","item_3":[50],"item_2":[236],"item_1":[212],"item_0":[116]},"skywrath_mage":{"kills":[1],"item_neutral":[0],"backpack_1":[0],"denies":[3],"backpack_2":[46],"backpack_0":[0],"leaves":0,"assists":[4],"loses":0,"xp_per_min":[296],"deaths":[0],"total_matches":2,"wins":1,"exp_per_min":[296],"gold_per_min":[364],"level":[9],"matches_id":[4102663752],"match_id":[4102663752],"friends":{"gela":{"wins":1,"loses":0,"total_matches":1},"knight":{"wins":1,"loses":0,"total_matches":1},"mati":{"wins":1,"loses":0,"total_matches":1}},"last_hits":[38],"item_5":[73],"item_4":[73],"name":"Skywrath Mage","item_3":[180],"item_2":[244],"item_1":[77],"item_0":[259]},"spectre":{"kills":[15],"item_neutral":[0],"backpack_1":[17],"denies":[19],"backpack_2":[0],"backpack_0":[21],"leaves":0,"assists":[22],"loses":0,"xp_per_min":[784],"deaths":[2],"total_matches":2,"wins":1,"exp_per_min":[784],"gold_per_min":[716],"level":[24],"matches_id":[3781635196],"match_id":[3781635196],"friends":{"gela":{"wins":1,"loses":0,"total_matches":1},"knight":{"wins":1,"loses":0,"total_matches":1}},"last_hits":[253],"item_5":[125],"item_4":[170],"name":"sPECTRE","item_3":[63],"item_2":[147],"item_1":[139],"item_0":[145]},"terrorblade":{"kills":[10,6],"item_neutral":[0,0],"backpack_1":[0,241],"denies":[8,11],"backpack_2":[0,0],"backpack_0":[63,182],"leaves":0,"assists":[10,5],"loses":0,"xp_per_min":[627,410],"deaths":[6,1],"total_matches":4,"wins":2,"exp_per_min":[627,410],"gold_per_min":[731,634],"level":[25,14],"matches_id":[3162464803,3672499597],"match_id":[3162464803,3672499597],"friends":{"gela":{"wins":2,"loses":0,"total_matches":2},"knight":{"wins":1,"loses":0,"total_matches":1}},"last_hits":[551,159],"item_5":[147,212],"item_4":[160,139],"name":"Terrorblade","item_3":[139,63],"item_2":[160,154],"item_1":[135,36],"item_0":[116,236]},"earthshaker":{"kills":[13,6,2,12,10,14,2,5,5],"item_neutral":[0,0,0,0,0,0,574,289,306],"backpack_1":[46,218,0,0,0,0,0,571,0],"denies":[1,15,11,19,24,13,6,11,2],"backpack_2":[0,0,0,0,0,0,0,0,0],"backpack_0":[36,0,0,40,0,38,0,349,0],"leaves":0,"assists":[11,16,4,11,30,26,6,24,17],"loses":2,"xp_per_min":[565,649,293,559,620,616,419,529,536],"deaths":[3,2,9,1,8,3,2,6,0],"total_matches":18,"wins":7,"exp_per_min":[565,649,293,559,620,616,419,529,536],"gold_per_min":[479,413,256,486,498,525,296,320,337],"level":[23,23,12,20,25,21,18,24,17],"matches_id":[3009392313,4430455425,4501596999,4987934286,4997416367,5127129539,5785538388,5791898658,5840223341],"match_id":[3009392313,4430455425,4501596999,4987934286,4997416367,5127129539,5785538388,5791898658,5840223341],"friends":{"gela":{"wins":7,"loses":2,"total_matches":9},"knight":{"wins":2,"loses":1,"total_matches":3},"sparki":{"wins":1,"loses":0,"total_matches":1}},"last_hits":[112,98,69,135,262,131,109,102,43],"item_5":[102,102,180,114,110,102,178,102,0],"item_4":[180,214,0,108,48,108,108,214,214],"name":"Earthshaker","item_3":[100,100,11,50,210,50,50,100,34],"item_2":[1,1,1,1,1,1,1,1,1],"item_1":[108,30,34,36,37,149,0,108,0],"item_0":[152,178,182,178,226,11,11,178,37]},"luna":{"kills":[13],"item_neutral":[0],"backpack_1":[0],"denies":[5],"backpack_2":[147],"backpack_0":[48],"leaves":0,"assists":[20],"loses":0,"xp_per_min":[765],"deaths":[8],"total_matches":2,"wins":1,"exp_per_min":[765],"gold_per_min":[744],"level":[25],"matches_id":[3217385424],"match_id":[3217385424],"friends":{"gela":{"wins":1,"loses":0,"total_matches":1},"knight":{"wins":1,"loses":0,"total_matches":1},"mati":{"wins":1,"loses":0,"total_matches":1}},"last_hits":[974],"item_5":[133],"item_4":[160],"name":"Luna","item_3":[176],"item_2":[156],"item_1":[112],"item_0":[116]},"slardar":{"kills":[2],"item_neutral":[0],"backpack_1":[0],"denies":[4],"backpack_2":[0],"backpack_0":[46],"leaves":0,"assists":[15],"loses":0,"xp_per_min":[541],"deaths":[5],"total_matches":2,"wins":1,"exp_per_min":[541],"gold_per_min":[342],"level":[20],"matches_id":[3601658769],"match_id":[3601658769],"friends":{"gela":{"wins":1,"loses":0,"total_matches":1},"knight":{"wins":1,"loses":0,"total_matches":1}},"last_hits":[48],"item_5":[102],"item_4":[214],"name":"Slardar","item_3":[36],"item_2":[1],"item_1":[40],"item_0":[37]},"riky":{"kills":[11],"item_neutral":[638],"backpack_1":[0],"denies":[4],"backpack_2":[0],"backpack_0":[63],"leaves":0,"assists":[17],"loses":0,"xp_per_min":[671],"deaths":[7],"total_matches":2,"wins":1,"exp_per_min":[671],"gold_per_min":[680],"level":[28],"matches_id":[5844043379],"match_id":[5844043379],"friends":{"gela":{"wins":1,"loses":0,"total_matches":1},"mati":{"wins":1,"loses":0,"total_matches":1}},"last_hits":[548],"item_5":[147],"item_4":[108],"name":"Riky","item_3":[133],"item_2":[208],"item_1":[141],"item_0":[145]},"techies":{"kills":[12,8,11,4,6,14,9,7,12,14,3,23,10,7,7,10,9,10,18,14,19],"item_neutral":[0,0,0,0,0,0,0,0,0,0,0,0,0,0,359,287,287,290,300,680,372],"backpack_1":[0,46,0,0,0,0,0,0,0,0,0,0,0,0,0,0,0,43,0,0,38],"denies":[3,4,2,4,2,1,7,1,0,1,1,1,0,1,0,0,0,0,0,1,2],"backpack_2":[0,0,0,0,0,0,0,0,0,0,0,0,0,0,40,0,0,0,100,0,39],"backpack_0":[65,36,0,0,0,0,0,0,244,0,0,0,0,24,21,0,0,188,216,287,245],"leaves":0,"assists":[16,8,13,9,12,12,0,4,12,13,5,11,9,16,6,4,3,7,17,7,5],"loses":8,"xp_per_min":[634,394,743,434,566,621,603,716,610,590,336,870,682,753,435,413,503,657,645,493,671],"deaths":[8,4,4,9,5,6,0,6,6,7,1,4,9,6,4,2,7,6,9,11,3],"total_matches":42,"wins":13,"exp_per_min":[634,394,743,434,566,621,603,716,610,590,336,870,682,753,435,413,503,657,645,493,671],"gold_per_min":[610,500,517,320,434,599,527,424,516,692,338,608,542,483,302,397,419,452,566,417,485],"level":[25,14,25,15,22,25,13,25,21,25,14,25,25,26,19,15,24,24,28,21,30],"matches_id":[3208353656,3765003187,4062209463,4081026737,4294154281,4638454442,4690153012,4743877416,5015321243,5038010293,5039429951,5045754487,5117683797,5149999296,5318368942,5785707740,5790352255,5798609946,5826446907,5840266195,5843954694],"match_id":[3208353656,3765003187,4062209463,4081026737,4294154281,4638454442,4690153012,4743877416,5015321243,5038010293,5039429951,5045754487,5117683797,5149999296,5318368942,5785707740,5790352255,5798609946,5826446907,5840266195,5843954694],"friends":{"gela":{"wins":13,"loses":8,"total_matches":21},"knight":{"wins":6,"loses":3,"total_matches":9},"sparki":{"wins":1,"loses":2,"total_matches":3},"mati":{"wins":6,"loses":4,"total_matches":10}},"last_hits":[358,79,147,51,143,282,62,167,94,407,71,273,156,145,74,66,267,147,274,192,172],"item_5":[102,102,108,0,102,108,77,57,218,123,108,135,180,178,38,0,108,232,235,178,48],"item_4":[220,77,48,0,77,48,180,108,232,232,232,141,108,218,214,214,214,214,220,214,98],"name":"Techies","item_3":[96,178,100,29,100,100,244,100,178,158,88,158,100,58,23,232,57,176,216,100,37],"item_2":[1,259,102,102,178,102,178,178,102,220,244,33,102,102,178,178,102,102,102,102,102],"item_1":[121,180,178,46,108,235,77,232,48,141,29,116,178,108,60,38,232,108,108,43,232],"item_0":[108,108,232,178,180,96,77,180,108,135,178,263,96,180,232,108,178,178,176,108,100]},"silencer":{"kills":[8],"item_neutral":[0],"backpack_1":[46],"denies":[1],"backpack_2":[0],"backpack_0":[0],"leaves":0,"assists":[7],"loses":0,"xp_per_min":[587],"deaths":[4],"total_matches":2,"wins":1,"exp_per_min":[587],"gold_per_min":[564],"level":[25],"matches_id":[3400680335],"match_id":[3400680335],"friends":{"gela":{"wins":1,"loses":0,"total_matches":1},"knight":{"wins":1,"loses":0,"total_matches":1}},"last_hits":[271],"item_5":[263],"item_4":[65],"name":"Silencer","item_3":[63],"item_2":[250],"item_1":[152],"item_0":[96]},"life_stealer":{"kills":[19,10,10,9,2],"item_neutral":[0,0,0,0,0],"backpack_1":[46,0,0,0,11],"denies":[22,20,13,8,9],"backpack_2":[0,0,0,11,0],"backpack_0":[239,0,46,0,0],"leaves":0,"assists":[18,6,13,8,5],"loses":3,"xp_per_min":[604,678,613,562,336],"deaths":[0,1,9,5,3],"total_matches":10,"wins":2,"exp_per_min":[604,678,613,562,336],"gold_per_min":[574,639,493,480,325],"level":[22,21,25,22,14],"matches_id":[3206414767,3400760532,3811901709,4357163125,5123996118],"match_id":[3206414767,3400760532,3811901709,4357163125,5123996118],"friends":{"gela":{"wins":2,"loses":3,"total_matches":5},"knight":{"wins":2,"loses":0,"total_matches":2},"mati":{"wins":1,"loses":1,"total_matches":2}},"last_hits":[175,198,415,260,121],"item_5":[168,249,249,73,8],"item_4":[252,71,168,73,73],"name":"Lifestealer","item_3":[50,50,225,63,50],"item_2":[151,151,147,249,151],"item_1":[30,117,252,168,240],"item_0":[208,168,63,252,65]},"pugna":{"kills":[8],"item_neutral":[0],"backpack_1":[46],"denies":[1],"backpack_2":[0],"backpack_0":[43],"leaves":0,"assists":[21],"loses":0,"xp_per_min":[590],"deaths":[7],"total_matches":2,"wins":1,"exp_per_min":[590],"gold_per_min":[399],"level":[25],"matches_id":[3969933998],"match_id":[3969933998],"friends":{"gela":{"wins":1,"loses":0,"total_matches":1},"knight":{"wins":1,"loses":0,"total_matches":1}},"last_hits":[167],"item_5":[108],"item_4":[48],"name":"Pugna","item_3":[100],"item_2":[37],"item_1":[232],"item_0":[59]},"bounty_hunter":{"kills":[2,18,8],"item_neutral":[0,381,287],"backpack_1":[0,638,0],"denies":[7,3,0],"backpack_2":[0,0,0],"backpack_0":[237,0,181],"leaves":0,"assists":[9,24,26],"loses":0,"xp_per_min":[319,613,645],"deaths":[1,9,3],"total_matches":6,"wins":3,"exp_per_min":[319,613,645],"gold_per_min":[371,593,512],"level":[9,27,23],"matches_id":[4253568663,5806294037,5823073225],"match_id":[4253568663,5806294037,5823073225],"friends":{"gela":{"wins":3,"loses":0,"total_matches":3},"sparki":{"wins":2,"loses":0,"total_matches":2}},"last_hits":[15,134,41],"item_5":[0,168,29],"item_4":[181,112,108],"name":"Bounty Hunter","item_3":[40,50,232],"item_2":[180,208,226],"item_1":[79,135,36],"item_0":[92,116,92]},"juggernaut":{"kills":[7,12,7,12,9,16,13],"item_neutral":[0,0,0,0,0,0,573],"backpack_1":[0,212,46,0,0,0,0],"denies":[21,23,31,12,40,16,5],"backpack_2":[0,0,0,0,0,0,0],"backpack_0":[36,0,43,0,0,0,50],"leaves":0,"assists":[7,17,10,11,7,31,10],"loses":1,"xp_per_min":[599,746,676,817,742,735,926],"deaths":[3,2,5,1,3,5,2],"total_matches":14,"wins":6,"exp_per_min":[599,746,676,817,742,735,926],"gold_per_min":[596,711,614,760,676,580,740],"level":[23,25,25,23,25,25,28],"matches_id":[3094993616,3221300197,3663215050,3734843310,4043233699,5026654155,5823202016],"match_id":[3094993616,3221300197,3663215050,3734843310,4043233699,5026654155,5823202016],"friends":{"gela":{"wins":6,"loses":1,"total_matches":7},"knight":{"wins":4,"loses":1,"total_matches":5},"sparki":{"wins":1,"loses":0,"total_matches":1}},"last_hits":[244,434,521,274,388,439,415],"item_5":[147,147,123,249,139,160,139],"item_4":[212,135,10,160,46,135,135],"name":"Juggernaut","item_3":[50,50,50,63,50,50,133],"item_2":[196,1,147,225,249,147,145],"item_1":[208,123,145,145,154,139,143],"item_0":[117,208,208,46,145,225,108]},"drow_ranger":{"kills":[12,9,3,5,6],"item_neutral":[0,0,0,0,0],"backpack_1":[0,0,0,0,0],"denies":[11,21,8,19,11],"backpack_2":[46,0,0,44,0],"backpack_0":[0,0,21,0,46],"leaves":0,"assists":[16,13,8,6,14],"loses":2,"xp_per_min":[638,683,363,495,595],"deaths":[5,5,8,0,5],"total_matches":10,"wins":3,"exp_per_min":[638,683,363,495,595],"gold_per_min":[673,545,443,645,563],"level":[25,25,18,15,22],"matches_id":[2912194206,3029576886,3212837209,3665285471,3994642130],"match_id":[2912194206,3029576886,3212837209,3665285471,3994642130],"friends":{"gela":{"wins":3,"loses":2,"total_matches":5},"knight":{"wins":3,"loses":1,"total_matches":4}},"last_hits":[333,294,170,155,259],"item_5":[263,263,263,172,263],"item_4":[139,108,212,212,139],"name":"Drow Ranger","item_3":[50,63,63,63,63],"item_2":[147,147,172,263,26],"item_1":[164,164,36,11,212],"item_0":[135,212,8,36,116]},"hoodwink":{"kills":[14,7,7,3],"item_neutral":[326,306,326,361],"backpack_1":[0,0,0,0],"denies":[4,8,2,1],"backpack_2":[0,0,0,0],"backpack_0":[42,0,0,0],"leaves":0,"assists":[28,11,17,14],"loses":3,"xp_per_min":[655,456,448,385],"deaths":[4,10,6,5],"total_matches":8,"wins":1,"exp_per_min":[655,456,448,385],"gold_per_min":[507,393,285,347],"level":[27,20,19,18],"matches_id":[5782984884,5785630841,5790277635,5801798101],"match_id":[5782984884,5785630841,5790277635,5801798101],"friends":{"gela":{"wins":1,"loses":3,"total_matches":4},"sparki":{"wins":1,"loses":2,"total_matches":3}},"last_hits":[217,194,51,163],"item_5":[160,36,188,166],"item_4":[214,75,214,596],"name":"Hookwink","item_3":[176,63,229,50],"item_2":[1466,598,102,139],"item_1":[1,41,36,75],"item_0":[596,1466,41,36]},"batrider":{"kills":[6],"item_neutral":[0],"backpack_1":[0],"denies":[5],"backpack_2":[0],"backpack_0":[0],"leaves":0,"assists":[13],"loses":0,"xp_per_min":[450],"deaths":[6],"total_matches":2,"wins":1,"exp_per_min":[450],"gold_per_min":[380],"level":[19],"matches_id":[3334677232],"match_id":[3334677232],"friends":{"gela":{"wins":1,"loses":0,"total_matches":1},"knight":{"wins":1,"loses":0,"total_matches":1},"mati":{"wins":1,"loses":0,"total_matches":1}},"last_hits":[99],"item_5":[102],"item_4":[214],"name":"Batrider","item_3":[100],"item_2":[1],"item_1":[43],"item_0":[185]},"spirit_breaker":{"kills":[8],"item_neutral":[0],"backpack_1":[0],"denies":[7],"backpack_2":[0],"backpack_0":[0],"leaves":0,"assists":[35],"loses":0,"xp_per_min":[621],"deaths":[8],"total_matches":2,"wins":1,"exp_per_min":[621],"gold_per_min":[400],"level":[25],"matches_id":[4957848057],"match_id":[4957848057],"friends":{"gela":{"wins":1,"loses":0,"total_matches":1},"knight":{"wins":1,"loses":0,"total_matches":1},"mati":{"wins":1,"loses":0,"total_matches":1}},"last_hits":[96],"item_5":[65],"item_4":[30],"name":"Spirit Breaker","item_3":[63],"item_2":[81],"item_1":[92],"item_0":[116]},"bloodseeker":{"kills":[12,8,12],"item_neutral":[0,0,0],"backpack_1":[0,11,0],"denies":[20,6,2],"backpack_2":[46,46,0],"backpack_0":[0,0,0],"leaves":0,"assists":[12,8,16],"loses":1,"xp_per_min":[727,629,697],"deaths":[4,8,4],"total_matches":6,"wins":2,"exp_per_min":[727,629,697],"gold_per_min":[643,508,536],"level":[23,24,25],"matches_id":[3478167191,3566082912,4294218965],"match_id":[3478167191,3566082912,4294218965],"friends":{"gela":{"wins":2,"loses":1,"total_matches":3},"knight":{"wins":2,"loses":1,"total_matches":3}},"last_hits":[268,257,225],"item_5":[154,137,135],"item_4":[137,212,52],"name":"Bloodseeker","item_3":[63,63,63],"item_2":[127,235,127],"item_1":[123,131,154],"item_0":[239,65,116]},"chen":{"kills":[2],"item_neutral":[0],"backpack_1":[0],"denies":[0],"backpack_2":[0],"backpack_0":[0],"leaves":0,"assists":[20],"loses":0,"xp_per_min":[344],"deaths":[7],"total_matches":2,"wins":1,"exp_per_min":[344],"gold_per_min":[320],"level":[19],"matches_id":[2964357083],"match_id":[2964357083],"friends":{"gela":{"wins":1,"loses":0,"total_matches":1}},"last_hits":[80],"item_5":[0],"item_4":[46],"name":"Chen","item_3":[188],"item_2":[108],"item_1":[42],"item_0":[231]},"slark":{"kills":[21,19,7,14,5,5],"item_neutral":[0,0,0,0,0,0],"backpack_1":[0,0,0,239,181,0],"denies":[13,9,6,9,14,13],"backpack_2":[0,0,0,46,0,265],"backpack_0":[0,46,46,181,24,46],"leaves":0,"assists":[9,8,10,17,18,8],"loses":0,"xp_per_min":[868,677,527,740,590,562],"deaths":[0,5,2,3,7,5],"total_matches":12,"wins":6,"exp_per_min":[868,677,527,740,590,562],"gold_per_min":[811,628,603,626,512,538],"level":[25,25,19,24,24,19],"matches_id":[2904033730,3101018809,3200717637,3213072070,3498591343,3672541665],"match_id":[2904033730,3101018809,3200717637,3213072070,3498591343,3672541665],"friends":{"gela":{"wins":6,"loses":0,"total_matches":6},"knight":{"wins":4,"loses":0,"total_matches":4}},"last_hits":[251,236,216,225,298,221],"item_5":[30,98,160,123,212,212],"item_4":[247,160,252,252,60,252],"name":"Slark","item_3":[63,63,63,63,63,63],"item_2":[249,249,249,249,249,249],"item_1":[247,71,36,212,239,36],"item_0":[208,116,239,30,116,11]},"omniknight":{"kills":[14],"item_neutral":[0],"backpack_1":[46],"denies":[9],"backpack_2":[0],"backpack_0":[178],"leaves":0,"assists":[6],"loses":0,"xp_per_min":[525],"deaths":[3],"total_matches":2,"wins":1,"exp_per_min":[525],"gold_per_min":[649],"level":[19],"matches_id":[4071034716],"match_id":[4071034716],"friends":{"gela":{"wins":1,"loses":0,"total_matches":1},"knight":{"wins":1,"loses":0,"total_matches":1}},"last_hits":[167],"item_5":[185],"item_4":[135],"name":"Omniknight","item_3":[50],"item_2":[212],"item_1":[137],"item_0":[127]},"mars":{"kills":[6,10,7,2],"item_neutral":[0,0,326,357],"backpack_1":[0,41,0,0],"denies":[17,21,11,19],"backpack_2":[0,182,38,0],"backpack_0":[182,36,0,0],"leaves":0,"assists":[19,24,18,4],"loses":1,"xp_per_min":[636,693,686,326],"deaths":[6,5,7,6],"total_matches":8,"wins":3,"exp_per_min":[636,693,686,326],"gold_per_min":[478,507,489,303],"level":[25,24,26,14],"matches_id":[4497774300,4498015320,5797070987,5797105568],"match_id":[4497774300,4498015320,5797070987,5797105568],"friends":{"gela":{"wins":3,"loses":1,"total_matches":4}},"last_hits":[226,182,220,128],"item_5":[73,73,210,11],"item_4":[81,81,73,81],"name":"Mars","item_3":[50,50,50,50],"item_2":[1,1,1,1],"item_1":[90,90,168,40],"item_0":[116,116,116,21]},"naga_siren":{"kills":[11,5,5],"item_neutral":[0,0,0],"backpack_1":[0,0,0],"denies":[12,9,10],"backpack_2":[112,0,0],"backpack_0":[0,0,0],"leaves":0,"assists":[35,16,11],"loses":0,"xp_per_min":[379,524,476],"deaths":[2,6,1],"total_matches":6,"wins":3,"exp_per_min":[379,524,476],"gold_per_min":[767,672,594],"level":[25,25,20],"matches_id":[2904187230,3116912387,3423032489],"match_id":[2904187230,3116912387,3423032489],"friends":{"gela":{"wins":3,"loses":0,"total_matches":3}},"last_hits":[864,530,337],"item_5":[160,147,147],"item_4":[220,48,48],"name":"Naga Siren","item_3":[114,174,212],"item_2":[137,139,0],"item_1":[235,235,137],"item_0":[147,137,235]},"lone_druid":{"kills":[2,13,8],"item_neutral":[0,0,0],"backpack_1":[16,0,0],"denies":[17,11,6],"backpack_2":[0,0,0],"backpack_0":[0,0,0],"leaves":0,"assists":[12,13,10],"loses":1,"xp_per_min":[510,621,575],"deaths":[2,3,7],"total_matches":6,"wins":2,"exp_per_min":[510,621,575],"gold_per_min":[632,629,493],"level":[16,24,24],"matches_id":[2916948033,3038066952,3080713047],"match_id":[2916948033,3038066952,3080713047],"friends":{"gela":{"wins":2,"loses":1,"total_matches":3}},"last_hits":[121,225,298],"item_5":[236,263,263],"item_4":[166,108,212],"name":"Lone Druid","item_3":[63,50,50],"item_2":[212,160,158],"item_1":[154,158,46],"item_0":[16,212,135]},"pangolier":{"kills":[13,11,4,1,13,7,21,8,12,6,3,4],"item_neutral":[0,0,0,0,0,0,0,0,0,0,0,0],"backpack_1":[73,0,0,0,0,0,140,0,0,11,0,0],"denies":[7,10,9,6,10,8,5,7,16,5,15,3],"backpack_2":[11,0,0,0,46,0,0,0,0,0,0,0],"backpack_0":[46,46,0,0,0,0,46,0,39,38,0,255],"leaves":0,"assists":[21,9,5,6,11,15,17,11,21,9,28,25],"loses":4,"xp_per_min":[707,714,454,386,794,512,673,627,759,493,570,613],"deaths":[9,0,9,8,2,2,7,8,3,9,5,17],"total_matches":24,"wins":8,"exp_per_min":[707,714,454,386,794,512,673,627,759,493,570,613],"gold_per_min":[574,594,398,347,669,492,655,399,659,444,396,521],"level":[23,21,21,15,25,17,25,23,25,23,23,25],"matches_id":[3547772016,3554917964,3554970891,3562620422,3790647321,3831720165,3843105318,4030383688,4497891174,4740658326,5009984891,5118893814],"match_id":[3547772016,3554917964,3554970891,3562620422,3790647321,3831720165,3843105318,4030383688,4497891174,4740658326,5009984891,5118893814],"friends":{"gela":{"wins":8,"loses":4,"total_matches":12},"knight":{"wins":6,"loses":3,"total_matches":9},"mati":{"wins":3,"loses":0,"total_matches":3}},"last_hits":[142,136,208,114,248,98,277,143,364,310,176,462],"item_5":[174,174,127,174,178,7,123,7,48,166,11,0],"item_4":[212,212,154,11,135,46,180,7,166,143,166,166],"name":"Pangolier","item_3":[63,50,50,63,63,79,158,0,141,226,231,226],"item_2":[1,1,1,0,1,1,1,1,1,231,1,1],"item_1":[36,36,212,36,141,180,135,123,135,36,34,231],"item_0":[208,208,174,212,208,135,149,180,123,182,116,208]},"earth_spirit":{"kills":[2,3],"item_neutral":[0,0],"backpack_1":[0,41],"denies":[1,13],"backpack_2":[0,11],"backpack_0":[0,36],"leaves":0,"assists":[22,17],"loses":0,"xp_per_min":[416,654],"deaths":[4,5],"total_matches":4,"wins":2,"exp_per_min":[416,654],"gold_per_min":[377,511],"level":[17,23],"matches_id":[3403176208,4670561829],"match_id":[3403176208,4670561829],"friends":{"gela":{"wins":2,"loses":0,"total_matches":2}},"last_hits":[57,138],"item_5":[102,102],"item_4":[65,81],"name":"Earth Spirit","item_3":[100,63],"item_2":[0,1],"item_1":[180,65],"item_0":[36,127]},"tinker":{"kills":[0,9,10,14],"item_neutral":[0,0,0,0],"backpack_1":[0,41,178,0],"denies":[21,9,6,7],"backpack_2":[0,0,0,0],"backpack_0":[0,0,41,0],"leaves":0,"assists":[3,21,16,17],"loses":1,"xp_per_min":[459,649,670,810],"deaths":[0,3,8,6],"total_matches":8,"wins":3,"exp_per_min":[459,649,670,810],"gold_per_min":[340,620,489,626],"level":[12,23,25,25],"matches_id":[2892974196,2965758981,3566187613,3766524768],"match_id":[2892974196,2965758981,3566187613,3766524768],"friends":{"gela":{"wins":3,"loses":1,"total_matches":4},"knight":{"wins":3,"loses":1,"total_matches":4}},"last_hits":[64,234,338,354],"item_5":[77,121,108,176],"item_4":[48,48,48,220],"name":"Tinker","item_3":[237,108,100,96],"item_2":[16,1,1,1],"item_1":[41,37,201,232],"item_0":[178,178,96,116]},"ancient_apparition":{"kills":[10,8],"item_neutral":[0,0],"backpack_1":[65,0],"denies":[3,7],"backpack_2":[0,0],"backpack_0":[46,46],"leaves":0,"assists":[21,20],"loses":0,"xp_per_min":[581,472],"deaths":[7,6],"total_matches":4,"wins":2,"exp_per_min":[581,472],"gold_per_min":[541,367],"level":[25,19],"matches_id":[3637707739,4043174767],"match_id":[3637707739,4043174767],"friends":{"gela":{"wins":2,"loses":0,"total_matches":2},"knight":{"wins":2,"loses":0,"total_matches":2}},"last_hits":[209,26],"item_5":[102,102],"item_4":[259,180],"name":"Ancient Apparition","item_3":[63,100],"item_2":[190,254],"item_1":[123,36],"item_0":[108,218]},"snapfire":{"kills":[5,12,16,6,2,8],"item_neutral":[0,0,0,364,290,326],"backpack_1":[0,0,0,0,0,0],"denies":[8,7,12,15,1,14],"backpack_2":[0,0,0,0,0,0],"backpack_0":[38,73,18,0,0,13],"leaves":0,"assists":[10,21,15,11,5,6],"loses":3,"xp_per_min":[599,579,499,539,299,585],"deaths":[4,5,1,11,4,5],"total_matches":12,"wins":3,"exp_per_min":[599,579,499,539,299,585],"gold_per_min":[474,430,509,379,229,423],"level":[21,21,17,25,11,22],"matches_id":[5146055867,5151239069,5151305760,5245358609,5783029323,5809278249],"match_id":[5146055867,5151239069,5151305760,5245358609,5783029323,5809278249],"friends":{"gela":{"wins":3,"loses":3,"total_matches":6},"knight":{"wins":1,"loses":0,"total_matches":1},"sparki":{"wins":1,"loses":2,"total_matches":3},"mati":{"wins":1,"loses":1,"total_matches":2}},"last_hits":[120,119,104,234,32,194],"item_5":[112,112,357,21,42,73],"item_4":[232,81,22,180,244,48],"name":"Snapfire","item_3":[50,357,259,206,214,108],"item_2":[206,36,36,263,102,1],"item_1":[40,90,231,166,0,41],"item_0":[36,180,90,73,178,37]},"antimage":{"kills":[7,10,10,4,15,1,1,22,5,13,23,8,6,4,4],"item_neutral":[0,0,0,0,0,0,0,0,0,0,0,0,0,0,680],"backpack_1":[0,0,0,0,145,0,22,46,0,0,10,0,0,0,27],"denies":[23,25,12,17,19,4,4,15,5,15,4,12,9,10,8],"backpack_2":[0,63,0,0,0,0,22,0,0,116,0,0,0,0,0],"backpack_0":[0,0,46,0,0,0,46,0,142,46,33,46,10,0,16],"leaves":0,"assists":[7,15,10,3,11,4,5,5,6,9,13,10,9,4,8],"loses":5,"xp_per_min":[803,650,879,693,868,524,496,941,625,864,811,752,702,393,670],"deaths":[0,3,2,1,3,6,4,5,1,0,2,0,8,1,2],"total_matches":30,"wins":10,"exp_per_min":[803,650,879,693,868,524,496,941,625,864,811,752,702,393,670],"gold_per_min":[897,802,833,685,790,421,538,777,567,826,778,810,607,356,656],"level":[25,25,24,24,25,18,22,25,19,25,25,22,25,13,21],"matches_id":[2906161356,3045670546,3094926877,3200594663,3408053496,3491681047,3523072236,3560971769,3601579750,3601612013,3605191370,3828613927,4359467626,4518210896,5803342449],"match_id":[2906161356,3045670546,3094926877,3200594663,3408053496,3491681047,3523072236,3560971769,3601579750,3601612013,3605191370,3828613927,4359467626,4518210896,5803342449],"friends":{"gela":{"wins":10,"loses":5,"total_matches":15},"knight":{"wins":8,"loses":3,"total_matches":11},"mati":{"wins":1,"loses":0,"total_matches":1}},"last_hits":[408,400,365,403,777,207,269,616,201,411,344,318,414,112,305],"item_5":[81,139,145,145,139,0,11,139,125,108,116,139,75,75,14],"item_4":[145,123,81,0,108,71,108,145,7,139,117,212,32,182,569],"name":"Anti-Mage","item_3":[63,81,63,63,48,63,63,63,63,63,63,63,63,63,63],"item_2":[147,147,147,147,147,36,147,147,147,147,147,147,147,75,147],"item_1":[108,145,0,81,116,145,65,116,46,145,145,108,145,0,145],"item_0":[208,208,208,208,208,239,208,208,145,208,208,145,208,145,208]},"monkey_king":{"kills":[18,6,7,6,12,16,8,9,10,4],"item_neutral":[0,0,0,0,0,0,0,0,0,0],"backpack_1":[212,0,43,11,0,0,40,0,0,0],"denies":[42,5,1,9,11,3,25,3,4,9],"backpack_2":[46,0,0,46,46,0,46,0,0,0],"backpack_0":[11,46,46,0,0,46,0,46,0,0],"leaves":1,"assists":[15,19,17,9,7,13,21,12,12,8],"loses":5,"xp_per_min":[765,569,626,543,638,658,592,773,615,406],"deaths":[4,4,6,3,10,6,7,10,8,12],"total_matches":20,"wins":5,"exp_per_min":[765,569,626,543,638,658,592,773,615,406],"gold_per_min":[559,499,408,561,580,585,504,549,469,320],"level":[25,24,25,19,25,22,25,25,25,17],"matches_id":[3530874406,3543726180,3543811153,3557226040,3562657606,3625852680,3805105640,3945126545,4031827677,5028114709],"match_id":[3530874406,3543726180,3543811153,3557226040,3562657606,3625852680,3805105640,3945126545,4031827677,5028114709],"friends":{"gela":{"wins":5,"loses":5,"total_matches":10},"knight":{"wins":5,"loses":3,"total_matches":8},"mati":{"wins":2,"loses":0,"total_matches":2}},"last_hits":[273,172,151,163,446,143,265,442,248,112],"item_5":[174,174,135,152,212,154,98,147,46,75],"item_4":[168,212,212,212,141,168,168,252,256,252],"name":"Monkey King","item_3":[50,50,50,50,50,50,63,63,63,50],"item_2":[152,225,223,174,135,152,249,210,249,8],"item_1":[135,65,65,65,123,212,212,145,145,36],"item_0":[116,208,116,131,145,135,116,116,116,21]},"grimstroke":{"kills":[11,6,2,5],"item_neutral":[0,0,0,36],"backpack_1":[46,266,0,43],"denies":[8,1,3,2],"backpack_2":[40,43,57,349],"backpack_0":[43,244,0,216],"leaves":0,"assists":[26,18,21,13],"loses":2,"xp_per_min":[579,419,485,484],"deaths":[3,7,12,11],"total_matches":8,"wins":2,"exp_per_min":[579,419,485,484],"gold_per_min":[489,409,422,362],"level":[22,17,24,19],"matches_id":[4087107075,4087458337,5043935300,5192435349],"match_id":[4087107075,4087458337,5043935300,5192435349],"friends":{"gela":{"wins":2,"loses":2,"total_matches":4},"knight":{"wins":1,"loses":0,"total_matches":1},"mati":{"wins":1,"loses":0,"total_matches":1}},"last_hits":[101,51,173,79],"item_5":[232,180,254,92],"item_4":[29,46,232,214],"name":"Grimstroke","item_3":[100,100,229,40],"item_2":[102,102,1,37],"item_1":[267,92,48,232],"item_0":[37,36,37,254]},"phantom_lancer":{"kills":[9],"item_neutral":[0],"backpack_1":[0],"denies":[5],"backpack_2":[0],"backpack_0":[0],"leaves":0,"assists":[15],"loses":0,"xp_per_min":[650],"deaths":[6],"total_matches":2,"wins":1,"exp_per_min":[650],"gold_per_min":[486],"level":[25],"matches_id":[4743739496],"match_id":[4743739496],"friends":{"gela":{"wins":1,"loses":0,"total_matches":1},"knight":{"wins":1,"loses":0,"total_matches":1},"mati":{"wins":1,"loses":0,"total_matches":1}},"last_hits":[261],"item_5":[147],"item_4":[0],"name":"Phantom Lancer","item_3":[63],"item_2":[174],"item_1":[160],"item_0":[131]},"sven":{"kills":[6],"item_neutral":[0],"backpack_1":[0],"denies":[11],"backpack_2":[0],"backpack_0":[46],"leaves":0,"assists":[11],"loses":0,"xp_per_min":[656],"deaths":[1],"total_matches":2,"wins":1,"exp_per_min":[656],"gold_per_min":[627],"level":[25],"matches_id":[3489789111],"match_id":[3489789111],"friends":{"gela":{"wins":1,"loses":0,"total_matches":1},"knight":{"wins":1,"loses":0,"total_matches":1}},"last_hits":[402],"item_5":[250],"item_4":[154],"name":"Sven","item_3":[63],"item_2":[1],"item_1":[172],"item_0":[116]},"sand_king":{"kills":[7,8,5,3,7],"item_neutral":[0,0,0,0,0],"backpack_1":[0,46,0,0,34],"denies":[3,3,4,3,13],"backpack_2":[0,0,38,0,0],"backpack_0":[0,0,0,0,0],"leaves":0,"assists":[24,8,22,10,15],"loses":0,"xp_per_min":[635,688,569,533,656],"deaths":[10,3,2,1,1],"total_matches":10,"wins":5,"exp_per_min":[635,688,569,533,656],"gold_per_min":[455,541,433,493,583],"level":[25,24,18,17,21],"matches_id":[3410122895,3857749841,4714214162,4724964129,5040945670],"match_id":[3410122895,3857749841,4714214162,4724964129,5040945670],"friends":{"gela":{"wins":5,"loses":0,"total_matches":5},"knight":{"wins":2,"loses":0,"total_matches":2},"mati":{"wins":2,"loses":0,"total_matches":2}},"last_hits":[208,216,94,144,187],"item_5":[102,102,214,50,90],"item_4":[108,48,81,73,108],"name":"Sand King","item_3":[100,100,100,100,50],"item_2":[1,1,90,242,1],"item_1":[46,108,92,11,223],"item_0":[180,232,36,127,190]},"pudge":{"kills":[10,4,8,9,6,11,4,12,5,3,7,15,17,12,4,6,14,5,3,0,12,9,7,11,8,1,1,2,6,10,8,5,9,12,11,6,17,9,7,6,12,11,9,16,5,2,12,6,8,6,11,11,9,13,7,9,9,11,6,10,5,10,5],"item_neutral":[0,0,0,0,0,0,0,0,0,0,0,0,0,0,0,0,0,0,0,0,0,0,0,0,0,0,0,0,0,0,0,0,0,0,0,0,0,0,0,0,0,0,0,0,0,0,0,0,0,0,0,0,0,0,0,0,0,0,326,365,336,571,381],"backpack_1":[21,0,0,178,0,178,0,46,0,0,0,41,0,218,0,0,46,0,0,0,0,0,0,46,0,0,0,0,46,42,0,0,0,36,11,0,0,0,0,36,0,0,0,46,0,0,0,57,0,0,0,0,0,0,0,0,0,0,306,43,73,0,0],"denies":[1,3,0,0,0,3,0,0,3,1,1,1,0,1,0,4,6,1,2,1,0,0,0,1,0,1,0,0,0,1,0,1,13,2,10,0,7,4,0,8,4,3,0,4,2,1,3,4,6,2,5,9,8,11,22,13,13,16,1,6,4,0,1],"backpack_2":[22,0,0,0,0,188,0,0,0,42,0,46,46,0,0,0,0,0,0,0,0,0,0,0,0,0,0,0,36,0,0,0,0,0,23,0,0,0,0,40,0,0,36,0,0,0,0,0,11,206,0,42,0,0,0,0,188,0,0,0,0,0,0],"backpack_0":[23,0,0,65,46,46,46,0,0,46,0,0,0,46,0,46,34,0,0,0,36,0,0,244,0,0,0,0,244,46,0,0,46,46,46,0,0,40,46,46,0,0,0,61,0,0,115,188,0,0,0,0,0,11,118,0,0,0,43,216,0,38,0],"leaves":1,"assists":[15,5,12,17,12,26,4,20,17,13,12,16,22,31,8,29,25,17,11,2,14,22,22,17,21,14,10,2,13,26,22,15,15,13,5,27,14,19,13,13,21,15,13,24,8,10,10,13,10,9,14,20,29,18,24,27,27,8,10,24,23,30,21],"loses":24,"xp_per_min":[570,357,476,580,429,537,411,570,472,531,416,548,706,557,432,494,736,359,386,226,467,579,555,438,477,432,228,111,449,564,517,334,551,541,519,628,633,454,427,565,497,520,516,623,354,335,580,463,585,415,474,672,777,627,641,551,657,714,380,557,642,558,539],"deaths":[5,6,2,8,9,4,4,11,7,5,7,11,3,7,11,7,7,10,15,2,4,0,9,10,9,8,3,4,4,7,6,17,3,4,11,13,7,10,5,7,13,5,0,5,5,7,10,14,7,4,2,13,3,0,4,3,4,0,8,7,8,8,3],"total_matches":126,"wins":39,"exp_per_min":[570,357,476,580,429,537,411,570,472,531,416,548,706,557,432,494,736,359,386,226,467,579,555,438,477,432,228,111,449,564,517,334,551,541,519,628,633,454,427,565,497,520,516,623,354,335,580,463,585,415,474,672,777,627,641,551,657,714,380,557,642,558,539],"gold_per_min":[456,391,353,514,392,446,329,426,327,376,354,414,486,463,286,425,502,273,299,484,403,407,351,330,378,297,266,252,336,457,421,262,476,479,382,473,552,373,366,468,448,412,434,504,237,234,406,376,468,366,468,611,584,552,482,448,476,506,259,364,440,351,329],"level":[25,15,25,25,22,25,21,25,21,21,17,24,23,25,18,25,25,20,20,6,18,20,21,21,19,19,10,6,19,25,25,15,20,17,20,25,25,24,17,19,25,14,18,23,17,17,24,22,22,14,18,25,25,20,25,21,25,19,18,27,26,27,19],"matches_id":[2922805526,3080641454,3100843333,3109488782,3114907584,3116837684,3123295193,3170624008,3172719691,3217118897,3240419371,3263444866,3293653012,3302124452,3312151251,3318600881,3324299443,3384013168,3489878752,3562590013,3585022534,3605095844,3609221379,3665325030,3667290627,3669100717,3697940892,3699543087,3705659388,3759557955,3781568274,3790688154,3823770313,3823804279,3823957928,3831647421,3831769375,3835395907,3857821981,3859787636,3859848924,3943432652,4070981374,4132627911,4352199932,4594343738,4670703071,4690482211,4948308379,5001618404,5026713725,5039465180,5044068437,5064043276,5068715734,5112086951,5114619538,5141730767,5220682965,5243389592,5800222021,5809319525,5811149222],"match_id":[2922805526,3080641454,3100843333,3109488782,3114907584,3116837684,3123295193,3170624008,3172719691,3217118897,3240419371,3263444866,3293653012,3302124452,3312151251,3318600881,3324299443,3384013168,3489878752,3562590013,3585022534,3605095844,3609221379,3665325030,3667290627,3669100717,3697940892,3699543087,3705659388,3759557955,3781568274,3790688154,3823770313,3823804279,3823957928,3831647421,3831769375,3835395907,3857821981,3859787636,3859848924,3943432652,4070981374,4132627911,4352199932,4594343738,4670703071,4690482211,4948308379,5001618404,5026713725,5039465180,5044068437,5064043276,5068715734,5112086951,5114619538,5141730767,5220682965,5243389592,5800222021,5809319525,5811149222],"friends":{"gela":{"wins":39,"loses":24,"total_matches":63},"knight":{"wins":27,"loses":10,"total_matches":37},"sparki":{"wins":3,"loses":0,"total_matches":3},"mati":{"wins":5,"loses":4,"total_matches":9}},"last_hits":[95,67,107,124,172,86,115,95,91,52,32,54,51,131,39,244,73,106,99,15,57,31,12,35,49,93,14,0,36,81,133,24,110,30,91,197,187,93,26,108,157,8,55,59,62,55,112,136,182,44,140,322,190,130,223,99,138,105,62,137,180,84,27],"item_5":[102,46,214,102,102,232,65,102,40,65,42,176,176,102,0,226,178,34,46,34,46,34,131,178,131,46,46,0,102,102,131,46,102,178,90,102,102,102,40,185,102,232,0,102,73,214,36,37,102,0,102,127,127,226,102,108,127,90,73,92,30,102,188],"item_4":[48,232,232,232,232,48,214,48,214,214,214,180,214,48,214,214,214,214,214,46,214,214,214,214,214,214,214,0,214,48,48,214,92,214,212,48,48,214,214,212,48,214,214,61,214,61,214,73,92,182,73,48,114,182,9,73,90,86,73,48,48,214,214],"name":"Pudge","item_3":[232,178,254,123,214,102,127,176,254,100,11,100,100,96,46,90,176,100,254,214,37,100,178,127,206,206,178,0,131,176,176,178,63,100,63,131,176,226,100,63,127,34,46,214,127,206,127,214,50,214,100,176,50,50,50,50,50,50,100,53,90,30,36],"item_2":[1,1,1,1,37,1,1,1,102,1,1,1,206,1,1,114,102,1,1,188,102,1,1,1,102,1,102,0,1,1,1,102,1,102,102,1,1,1,102,1,1,23,1,1,73,36,206,127,1,0,1,1,1,1,1,206,1,1,214,1,1,1,102],"item_1":[30,244,108,108,65,90,254,90,92,34,178,30,92,30,65,81,168,178,92,244,267,92,46,90,36,254,244,0,92,178,0,92,131,30,36,267,0,256,92,92,116,92,267,267,36,244,267,65,90,34,242,267,242,267,90,36,176,267,92,90,92,232,92],"item_0":[254,214,90,214,108,108,36,254,226,254,254,92,178,90,178,210,108,90,65,92,232,127,267,42,178,36,36,0,30,210,116,36,37,232,244,176,116,37,37,127,176,46,127,176,37,92,8,267,116,267,50,116,176,36,176,210,116,36,36,116,116,92,692]},"faceless_void":{"kills":[22,8,2,10,8,4],"item_neutral":[0,0,0,0,0,309],"backpack_1":[26,0,46,0,0,0],"denies":[8,23,20,8,13,2],"backpack_2":[0,0,0,0,0,0],"backpack_0":[63,46,157,0,0,0],"leaves":0,"assists":[13,14,6,18,12,17],"loses":2,"xp_per_min":[722,659,412,657,496,683],"deaths":[9,6,6,2,3,4],"total_matches":12,"wins":4,"exp_per_min":[722,659,412,657,496,683],"gold_per_min":[714,622,394,488,485,481],"level":[25,24,19,25,20,25],"matches_id":[3478083478,3479960456,3504835472,3761316749,4352135760,5320641421],"match_id":[3478083478,3479960456,3504835472,3761316749,4352135760,5320641421],"friends":{"gela":{"wins":4,"loses":2,"total_matches":6},"knight":{"wins":4,"loses":1,"total_matches":5}},"last_hits":[389,329,251,189,219,250],"item_5":[139,147,75,147,75,166],"item_4":[123,212,166,135,81,75],"name":"Faceless Void","item_3":[117,63,63,63,63,63],"item_2":[141,26,172,152,36,147],"item_1":[145,139,239,185,123,108],"item_0":[116,123,116,46,154,116]}},"assists":0,"loses":104,"denies":3226,"deaths":1969,"friends":{"gela":{"wins":282,"loses":104,"total_matches":386},"knight":{"wins":171,"loses":41,"total_matches":212},"sparki":{"wins":22,"loses":10,"total_matches":32},"mati":{"wins":50,"loses":14,"total_matches":64}},"total_matches":386}